mergerpy/__init__.py
mergerpy/merger.py
mergerpy-0.2.dist-info/DESCRIPTION.rst
mergerpy-0.2.dist-info/METADATA
mergerpy-0.2.dist-info/RECORD
mergerpy-0.2.dist-info/WHEEL
mergerpy-0.2.dist-info/metadata.json
mergerpy-0.2.dist-info/top_level.txt
