Metadata-Version: 2.0
Name: mergerpy
Version: 0.2
Summary: A library that provides text concatenation from given files
Home-page: https://github.com/abdullahselek/MergerPy
Author: Abdullah Selek
Author-email: abdullahselek@gmail.com
License: MIT License
Download-URL: https://github.com/abdullahselek/MergerPy
Keywords: merge strings,concatenate keywords,bitcoin wallets
Platform: Any
Classifier: Intended Audience :: Developers
Classifier: License :: OSI Approved :: MIT License
Classifier: Operating System :: OS Independent
Classifier: Topic :: Software Development :: Libraries :: Python Modules
Classifier: Programming Language :: Python
Classifier: Programming Language :: Python :: 2.7
Classifier: Programming Language :: Python :: 3.2
Classifier: Programming Language :: Python :: 3.3
Classifier: Programming Language :: Python :: 3.4
Classifier: Programming Language :: Python :: 3.5
Classifier: Programming Language :: Python :: 3.6
